MANIFEST.in
setup.py
shoal-server
conf/repo.conf
conf/shoal-server.logrotate
conf/shoal.conf
conf/shoal_server.conf
conf/scripts/setup_files.py
conf/scripts/shoal_wsgi.py
shoal_server/__init__.py
shoal_server/__version__.py
shoal_server/config.py
shoal_server/shoal.py
shoal_server/utilities.py
shoal_server/view.py
shoal_server.egg-info/PKG-INFO
shoal_server.egg-info/SOURCES.txt
shoal_server.egg-info/dependency_links.txt
shoal_server.egg-info/requires.txt
shoal_server.egg-info/top_level.txt
static/css/bootstrap-responsive.min.css
static/css/bootstrap.min.css
static/img/glyphicons-halflings-white.png
static/img/glyphicons-halflings.png
static/img/icons/favicon.ico
static/js/bootstrap.min.js
static/js/jquery.min.js
templates/base.html
templates/index.html
templates/wpad.dat