Metadata-Version: 1.0
Name: shoal-server
Version: 0.7.6
Summary: A squid cache publishing and advertising tool designed to work in fast changing environments
Home-page: http://github.com/hep-gc/shoal
Author: Mike Chester, Colson Drimiel, Ian Gable, Alex Lam, Rob Prior, Ryan Taylor
Author-email: igable@uvic.ca
License: 'GPL3' or 'Apache 2'
Platform: UNKNOWN
